setup.py
sdt_probability/Binomialdistribution.py
sdt_probability/Gaussiandistribution.py
sdt_probability/Generaldistribution.py
sdt_probability/__init__.py
sdt_probability.egg-info/PKG-INFO
sdt_probability.egg-info/SOURCES.txt
sdt_probability.egg-info/dependency_links.txt
sdt_probability.egg-info/not-zip-safe
sdt_probability.egg-info/top_level.txt