Metadata-Version: 1.0
Name: sdt-probability
Version: 0.1
Summary: Gaussian,General and Binomial distributions
Home-page: UNKNOWN
Author: Soubhik Das
Author-email: info@soubhikdas.me
License: UNKNOWN
Platform: UNKNOWN
